ontogpt/__init__.py
ontogpt/cli.py
ontogpt/clients/__init__.py
ontogpt/clients/llm_client.py
ontogpt/clients/pubmed_client.py
ontogpt/clients/soup_client.py
ontogpt/clients/wikipedia_client.py
ontogpt/converters/__init__.py
ontogpt/converters/ontology_converter.py
ontogpt/engines/__init__.py
ontogpt/engines/embedding_similarity_engine.py
ontogpt/engines/generic_engine.py
ontogpt/engines/halo_engine.py
ontogpt/engines/knowledge_engine.py
ontogpt/engines/mapping_engine.py
ontogpt/engines/pheno_engine.py
ontogpt/engines/reasoner_engine.py
ontogpt/engines/resolver.py
ontogpt/engines/spires_engine.py
ontogpt/engines/synonym_engine.py
ontogpt/engines/topic_classifier_engine.py
ontogpt/evaluation/__init__.py
ontogpt/evaluation/evaluation_engine.py
ontogpt/evaluation/resolver.py
ontogpt/evaluation/ctd/__init__.py
ontogpt/evaluation/ctd/eval_ctd.py
ontogpt/evaluation/ctd/eval_ctd_ner.py
ontogpt/evaluation/drugmechdb/__init__.py
ontogpt/evaluation/drugmechdb/eval_drugmechdb.py
ontogpt/evaluation/drugmechdb/datamodel/drugmechdb.py
ontogpt/evaluation/go/eval_go.py
ontogpt/evaluation/hpoa/__init__.py
ontogpt/evaluation/hpoa/eval_hpoa.py
ontogpt/evaluation/maxo/__init__.py
ontogpt/evaluation/maxo/eval_maxo.py
ontogpt/io/__init__.py
ontogpt/io/csv_exporter.py
ontogpt/io/csv_wrapper.py
ontogpt/io/exporter.py
ontogpt/io/html_exporter.py
ontogpt/io/json_wrapper.py
ontogpt/io/markdown_exporter.py
ontogpt/io/owl_exporter.py
ontogpt/io/rdf_exporter.py
ontogpt/io/template_loader.py
ontogpt/io/utils.py
ontogpt/io/yaml_wrapper.py
ontogpt/ontex/__init__.py
ontogpt/ontex/extractor.py
ontogpt/prompts/__init__.py
ontogpt/prompts/enrichment/__init__.py
ontogpt/prompts/mapping/__init__.py
ontogpt/prompts/phenopacket/__init__.py
ontogpt/prompts/qa/__init__.py
ontogpt/prompts/reasoning/__init__.py
ontogpt/templates/__init__.py
ontogpt/templates/adverse_outcome_pathway.py
ontogpt/templates/adverse_outcome_pathway.yaml
ontogpt/templates/all_disease_grounding.py
ontogpt-1.0.19.dist-info/licenses/LICENSE
ontogpt-1.0.19.dist-info/METADATA
ontogpt-1.0.19.dist-info/WHEEL
ontogpt-1.0.19.dist-info/entry_points.txt
ontogpt-1.0.19.dist-info/top_level.txt
ontogpt-1.0.19.dist-info/RECORD
