Metadata-Version: 2.4
Name: ontogpt
Version: 1.0.19
Summary: OntoGPT is a Python package for extracting structured information from text with large language models (LLMs), instruction prompts, and ontology-based grounding.
Author-email: Chris Mungall <cjmungall@lbl.gov>, "J. Harry Caufield" <jhc@lbl.gov>
License: BSD-3
Requires-Python: !=3.9.7,<3.14,>=3.9
License-File: LICENSE
Requires-Dist: ruamel-yaml>=0.17.31
Requires-Dist: aiohttp>=3.8.4
Requires-Dist: beautifulsoup4>=4.11.1
Requires-Dist: bioc>=2.0
Requires-Dist: cachier>=2.1.0
Requires-Dist: click>=8.1.3
Requires-Dist: inflect>=6.0.2
Requires-Dist: inflection>=0.5.1
Requires-Dist: linkml>=1.9.3-rc1
Requires-Dist: linkml-owl<1.0.0,>=0.3.0
Requires-Dist: oaklib>=0.5.28
Requires-Dist: pydantic>=2.4.0
Requires-Dist: requests<3.0.0,>=2.31.0
Requires-Dist: requests-cache>=1.2.0
Requires-Dist: tiktoken>=0.7.0
Requires-Dist: wikipedia>=1.4.0
Requires-Dist: wikipedia-api>=0.5.8
Requires-Dist: dpath<3.0.0,>=2.1.6
Requires-Dist: toml>=0.10.2
Requires-Dist: frontend>=0.0.3
Requires-Dist: litellm[caching]>=1.81.4
Requires-Dist: diskcache<6.0.0,>=5.6.3
Requires-Dist: pymupdf<2.0.0,>=1.24.9
Requires-Dist: scipy<2.0.0,>=1.13.0; python_version < "3.13"
Requires-Dist: scipy<2.0.0,>=1.14.1; python_version >= "3.13"
Requires-Dist: numpy<2.1,>=1.23; python_version < "3.13"
Requires-Dist: numpy>=2.0.0; python_version >= "3.13"
Dynamic: license-file
